click_pathlib/__init__.py
click_pathlib/py.typed
click_pathlib-2020.3.13.0.dist-info/LICENSE
click_pathlib-2020.3.13.0.dist-info/METADATA
click_pathlib-2020.3.13.0.dist-info/WHEEL
click_pathlib-2020.3.13.0.dist-info/top_level.txt
click_pathlib-2020.3.13.0.dist-info/RECORD
