Metadata-Version: 2.1
Name: click-pathlib
Version: 2020.3.13.0
Summary: 'A Python click type which is similar to click.Path but returns a pathlib Path'
Home-page: https://github.com/adamtheturtle/click-pathlib
Author: Adam Dangoor
Author-email: adamdangoor@gmail.com
License: Apache License, Version 2.0
Keywords: click
Platform: UNKNOWN
Classifier: Operating System :: POSIX
Classifier: Environment :: Web Environment
Classifier: Programming Language :: Python :: 3.8
Classifier: License :: OSI Approved :: Apache Software License
Classifier: Development Status :: 5 - Production/Stable
Requires-Dist: click (>=7.0)
Provides-Extra: dev
Requires-Dist: PyGithub (==1.46) ; extra == 'dev'
Requires-Dist: autoflake (==1.3.1) ; extra == 'dev'
Requires-Dist: check-manifest (==0.41) ; extra == 'dev'
Requires-Dist: codecov (==2.0.16) ; extra == 'dev'
Requires-Dist: flake8-commas (==2.0.0) ; extra == 'dev'
Requires-Dist: flake8-quotes (==2.1.1) ; extra == 'dev'
Requires-Dist: flake8 (==3.7.9) ; extra == 'dev'
Requires-Dist: isort (==4.3.21) ; extra == 'dev'
Requires-Dist: mypy (==0.770) ; extra == 'dev'
Requires-Dist: pip-check-reqs-pip-gte-20 (==2.0.3.1) ; extra == 'dev'
Requires-Dist: pydocstyle (==5.0.2) ; extra == 'dev'
Requires-Dist: pyenchant (==3.0.1) ; extra == 'dev'
Requires-Dist: pylint (==2.4.4) ; extra == 'dev'
Requires-Dist: pyroma (==2.6) ; extra == 'dev'
Requires-Dist: pytest-cov (==2.8.1) ; extra == 'dev'
Requires-Dist: pytest (==5.4.0) ; extra == 'dev'
Requires-Dist: twine (==3.1.1) ; extra == 'dev'
Requires-Dist: vulture (==1.3) ; extra == 'dev'
Requires-Dist: yapf (==0.29.0) ; extra == 'dev'
